etana_trade_mcp/__init__.py
etana_trade_mcp/main.py
etana_trade_mcp/server-v1.py
etana_trade_mcp/server.py
etana_trade_mcp-0.1.48.dist-info/METADATA
etana_trade_mcp-0.1.48.dist-info/WHEEL
etana_trade_mcp-0.1.48.dist-info/entry_points.txt
etana_trade_mcp-0.1.48.dist-info/top_level.txt
etana_trade_mcp-0.1.48.dist-info/RECORD
