Metadata-Version: 2.4
Name: etana-trade-mcp
Version: 0.1.48
Summary: MCP server that talks to the Etana Trade system to provide tool functions like, get user information and get account information from userId
Author-email: dennisnotojr <dennisnoto@gmail.com>
Requires-Python: >=3.13
Requires-Dist: httpx>=0.28.1
Requires-Dist: mcp[cli]>=1.10.1
Requires-Dist: pycryptodome>=3.23
Requires-Dist: pandas>=2.3
Requires-Dist: fastmcp>=2.10
Requires-Dist: pydantic>=2.11
Requires-Dist: requests>=2.32
